llama_index/postprocessor/openvino_rerank/__init__.py
llama_index/postprocessor/openvino_rerank/base.py
llama_index_postprocessor_openvino_rerank-0.5.0.dist-info/METADATA
llama_index_postprocessor_openvino_rerank-0.5.0.dist-info/WHEEL
llama_index_postprocessor_openvino_rerank-0.5.0.dist-info/licenses/LICENSE
llama_index_postprocessor_openvino_rerank-0.5.0.dist-info/RECORD
