Metadata-Version: 2.4
Name: llama-index-postprocessor-openvino-rerank
Version: 0.5.0
Summary: llama-index postprocessor openvino rerank integration
Author-email: Your Name <you@example.com>
License-Expression: MIT
License-File: LICENSE
Requires-Python: <4.0,>=3.9
Requires-Dist: huggingface-hub>=0.23.0
Requires-Dist: llama-index-core<0.14,>=0.13.0
Requires-Dist: optimum[openvino]<2,>=1.21.2
